{
  "$schema" : "https://schema.management.azure.com/schemas/2015-01-01/deploymentTemplate.json#",
  "contentVersion" : "1.0.0.0",
  "parameters" : {
    "image" : {
      "type" : "string",
      "metadata" : {
        "description" : "OS to use."
      }
    },
    "BootstrapIgnition" : {
      "type" : "string",
      "minLength" : 1,
      "metadata" : {
        "description" : "User name for the Virtual Machine and OpenShift Webconsole."
      }
    },
    "MasterIgnition" : {
      "type" : "string",
      "metadata" : {
        "description" : "User password for the OpenShift Webconsole"
      }
    },
    "WorkerIgnition" : {
      "type" : "string",
      "metadata" : {
        "description" : "User password for the OpenShift Webconsole"
      }
    },
    "numberOfNodes" : {
      "type" : "int",
      "defaultValue" : 3,
      "minValue" : 2,
      "maxValue" : 30,
      "metadata" : {
        "description" : "Number of OpenShift Nodes to deploy (max 30)"
      }
    },
    "sshKeyData" : {
      "type" : "securestring",
      "metadata" : {
        "description" : "SSH RSA public key file as a string."
      }
    },
    "masterVMSize" : {
      "type" : "string",
      "defaultValue" : "Standard_D8_v3",
      "allowedValues" : [
        "Standard_A2",
        "Standard_A3",
        "Standard_A4",
        "Standard_A5",
        "Standard_A6",
        "Standard_A7",
        "Standard_A8",
        "Standard_A9",
        "Standard_A10",
        "Standard_A11",
        "Standard_D2",
        "Standard_D3",
        "Standard_D4",
        "Standard_D11",
        "Standard_D12",
        "Standard_D13",
        "Standard_D14",
        "Standard_D2_v2",
        "Standard_D3_v2",
        "Standard_D4_v2",
        "Standard_D5_v2",
        "Standard_D8_v3",
        "Standard_D11_v2",
        "Standard_D12_v2",
        "Standard_D13_v2",
        "Standard_D14_v2",
        "Standard_E2_v3",
        "Standard_E4_v3",
        "Standard_E8_v3",
        "Standard_E16_v3",
        "Standard_E32_v3",
        "Standard_E64_v3",
        "Standard_E2s_v3",
        "Standard_E4s_v3",
        "Standard_E8s_v3",
        "Standard_E16s_v3",
        "Standard_E32s_v3",
        "Standard_E64s_v3",
        "Standard_G1",
        "Standard_G2",
        "Standard_G3",
        "Standard_G4",
        "Standard_G5",
        "Standard_DS2",
        "Standard_DS3",
        "Standard_DS4",
        "Standard_DS11",
        "Standard_DS12",
        "Standard_DS13",
        "Standard_DS14",
        "Standard_DS2_v2",
        "Standard_DS3_v2",
        "Standard_DS4_v2",
        "Standard_DS5_v2",
        "Standard_DS11_v2",
        "Standard_DS12_v2",
        "Standard_DS13_v2",
        "Standard_DS14_v2",
        "Standard_GS1",
        "Standard_GS2",
        "Standard_GS3",
        "Standard_GS4",
        "Standard_GS5",
        "Standard_D2s_v3",
        "Standard_D4s_v3",
        "Standard_D8s_v3"
      ],
      "metadata" : {
        "description" : "The size of the Master Virtual Machine."
      }
    },
    "nodeVMSize" : {
      "type" : "string",
      "defaultValue" : "Standard_D8_v3",
      "allowedValues" : [
        "Standard_A2",
        "Standard_A3",
        "Standard_A4",
        "Standard_A5",
        "Standard_A6",
        "Standard_A7",
        "Standard_A8",
        "Standard_A9",
        "Standard_A10",
        "Standard_A11",
        "Standard_D2",
        "Standard_D3",
        "Standard_D4",
        "Standard_D11",
        "Standard_D12",
        "Standard_D13",
        "Standard_D14",
        "Standard_D2_v2",
        "Standard_D3_v2",
        "Standard_D4_v2",
        "Standard_D5_v2",
        "Standard_D8_v3",
        "Standard_D11_v2",
        "Standard_D12_v2",
        "Standard_D13_v2",
        "Standard_D14_v2",
        "Standard_E2_v3",
        "Standard_E4_v3",
        "Standard_E8_v3",
        "Standard_E16_v3",
        "Standard_E32_v3",
        "Standard_E64_v3",
        "Standard_E2s_v3",
        "Standard_E4s_v3",
        "Standard_E8s_v3",
        "Standard_E16s_v3",
        "Standard_E32s_v3",
        "Standard_E64s_v3",
        "Standard_G1",
        "Standard_G2",
        "Standard_G3",
        "Standard_G4",
        "Standard_G5",
        "Standard_DS2",
        "Standard_DS3",
        "Standard_DS4",
        "Standard_DS11",
        "Standard_DS12",
        "Standard_DS13",
        "Standard_DS14",
        "Standard_DS2_v2",
        "Standard_DS3_v2",
        "Standard_DS4_v2",
        "Standard_DS5_v2",
        "Standard_DS11_v2",
        "Standard_DS12_v2",
        "Standard_DS13_v2",
        "Standard_DS14_v2",
        "Standard_GS1",
        "Standard_GS2",
        "Standard_GS3",
        "Standard_GS4",
        "Standard_GS5",
        "Standard_D2s_v3",
        "Standard_D4s_v3",
        "Standard_D8s_v3"
      ],
      "metadata" : {
        "description" : "The size of the each Node Virtual Machine."
      }
    }
  },
  "variables" : {
    "gituser" : "fabianofranz",
    "branch" : "cors-1249-azure-upi",
    "baseTemplateUrl" : "[concat('https://raw.githubusercontent.com/',variables('gituser'),'/installer/',variables('branch'),'/upi/azure/')]",
    "baseVMachineTemplateUriNode" : "[concat(variables('baseTemplateUrl'), 'node.json')]",
    "baseVMachineTemplateUriMaster" : "[concat(variables('baseTemplateUrl'), 'master.json')]",
    "virtualNetworkName" : "openshiftVnet",
    "nodesubnetName" : "nodeSubnet",
    "mastersubnetName" : "masterSubnet",
    "nodeStorageName" : "[concat('sa', resourceGroup().name)]",
    "vnetId" : "[resourceId('Microsoft.Network/virtualNetworks', variables('virtualNetworkName'))]",
    "nodeSubnetRef" : "[concat(variables('vnetId'), '/subnets/', variables('nodesubnetName'))]",
    "masterSubnetRef" : "[concat(variables('vnetId'), '/subnets/', variables('mastersubnetName'))]",
    "masterLoadBalancerName" : "[concat('MasterLb',resourceGroup().name)]",
    "infraLoadBalancerName" : "[concat('AppLb',resourceGroup().name)]"
  },
  "resources" : [
    {
      "name" : "[concat('node', copyindex())]",
      "type" : "Microsoft.Resources/deployments",
      "apiVersion" : "2015-01-01",
      "copy" : {
        "name" : "nodeSet",
        "count" : "[parameters('numberOfNodes')]"
      },
      "properties" : {
        "mode" : "Incremental",
        "templateLink" : {
          "uri" : "[variables('baseVMachineTemplateUriNode')]",
          "contentVersion" : "1.0.0.0"
        },
        "parameters" : {
          "vmName" : {
            "value" : "[concat('node', padLeft(add(copyindex(), 1), 2, '0'))]"
          },
          "sa" : {
            "value" : "[variables('nodeStorageName')]"
          },
          "subnetRef" : {
            "value" : "[variables('nodeSubnetRef')]"
          },
          "vmSize" : {
            "value" : "[parameters('nodeVMSize')]"
          },
          "ignition" : {
            "value" : "[parameters('WorkerIgnition')]"
          },
          "imageReference" : {
            "value" : "[parameters('image')]"
          },
          "infraLoadBalancerName" : {
            "value" : "[variables('infraLoadBalancerName')]"
          },
          "availabilitySet" : {
            "value" : "nodeavailabilityset"
          },
          "sshKeyData" : {
            "value" : "[parameters('sshKeyData')]"
          }
        }
      }
    },
    {
      "name" : "[concat('master', copyindex())]",
      "type" : "Microsoft.Resources/deployments",
      "apiVersion" : "2015-01-01",
      "copy" : {
        "name" : "masterSet",
        "count" : 3
      },
      "properties" : {
        "mode" : "Incremental",
        "templateLink" : {
          "uri" : "[variables('baseVMachineTemplateUriMaster')]",
          "contentVersion" : "1.0.0.0"
        },
        "parameters" : {
          "vmName" : {
            "value" : "[concat('master', padLeft(add(copyindex(), 1), 2, '0'))]"
          },
          "sa" : {
            "value" : "[variables('nodeStorageName')]"
          },
          "subnetRef" : {
            "value" : "[variables('masterSubnetRef')]"
          },
          "vmSize" : {
            "value" : "[parameters('masterVMSize')]"
          },
          "ignition" : {
            "value" : "[parameters('MasterIgnition')]"
          },
          "imageReference" : {
            "value" : "[parameters('image')]"
          },
          "masterLoadBalancerName" : {
            "value" : "[variables('masterLoadBalancerName')]"
          },
          "availabilitySet" : {
            "value" : "masteravailabilityset"
          },
          "sshKeyData" : {
            "value" : "[parameters('sshKeyData')]"
          },
          "ipAddress" : {
            "value" : "[concat('10.0.0.', add(copyindex(), 5))]"
          }
        }
      }
    }
  ],
  "outputs" : {
    "Openshift Webconsole" : {
      "type" : "string",
      "value" : "[concat('https://', 'TODO', ':8443/console')]"
    }
  }
}